PyTLidar/__init__.py
PyTLidar/main.py
PyTLidar/treeqsm.py
PyTLidar/treeqsm_batch.py
PyTLidar/TreeQSMSteps/LSF.py
PyTLidar/TreeQSMSteps/__init__.py
PyTLidar/TreeQSMSteps/branches.py
PyTLidar/TreeQSMSteps/correct_segments.py
PyTLidar/TreeQSMSteps/cover_sets.py
PyTLidar/TreeQSMSteps/cube_volume.py
PyTLidar/TreeQSMSteps/cylinders.py
PyTLidar/TreeQSMSteps/point_model_distance.py
PyTLidar/TreeQSMSteps/relative_size.py
PyTLidar/TreeQSMSteps/segments.py
PyTLidar/TreeQSMSteps/tree_data.py
PyTLidar/TreeQSMSteps/tree_sets.py
PyTLidar/Utils/RobustCylinderFitting.py
PyTLidar/Utils/TreeSegmentation.py
PyTLidar/Utils/Utils.py
PyTLidar/Utils/__init__.py
PyTLidar/Utils/define_input.py
PyTLidar/plotting/PlottingUtils.py
PyTLidar/plotting/__init__.py
PyTLidar/plotting/cylinders_line_plotting.py
PyTLidar/plotting/cylinders_plotting.py
PyTLidar/plotting/point_cloud_plotting.py
PyTLidar/plotting/qsm_plotting.py
PyTLidar/plotting/visualize_point_cloud.py
pytlidar-1.0.1.dist-info/METADATA
pytlidar-1.0.1.dist-info/WHEEL
pytlidar-1.0.1.dist-info/top_level.txt
pytlidar-1.0.1.dist-info/RECORD
