Metadata-Version: 2.4
Name: PyTLidar
Version: 1.0.1
Home-page: https://github.com/Landscape-CV/PyTLidar
Author: John Hagood
Classifier: Programming Language :: Python :: 3
Classifier: License :: OSI Approved :: GNU General Public License v3 (GPLv3)
Classifier: Operating System :: OS Independent
Requires-Python: >=3.8
Requires-Dist: alphashape
Requires-Dist: laspy[laszip,lazrs]
Requires-Dist: matplotlib
Requires-Dist: numba==0.61.2
Requires-Dist: numpy>=2.0
Requires-Dist: open3d
Requires-Dist: pandas>=2.0
Requires-Dist: plotly
Requires-Dist: PySide6==6.8.3
Requires-Dist: python-dotenv
Requires-Dist: igraph
Requires-Dist: scikit_learn
Requires-Dist: scipy
Dynamic: author
Dynamic: classifier
Dynamic: home-page
Dynamic: requires-dist
Dynamic: requires-python
